pier_ds_utils/__init__.py
pier_ds_utils/estimator.py
pier_ds_utils/predictor.py
pier_ds_utils/prep.py
pier_ds_utils/transformer.py
pier_ds_utils-0.6.0.dist-info/METADATA
pier_ds_utils-0.6.0.dist-info/WHEEL
pier_ds_utils-0.6.0.dist-info/RECORD
