Metadata-Version: 2.1
Name: pier-ds-utils
Version: 0.6.0
Summary: A library for data science teams to avoid code duplication in common tasks involving scikit-learn transformers and estimators.
Author: Gabriel Guarisa
Author-email: gabriel.guarisa@pier.digital
Requires-Python: >=3.9,<3.12
Classifier: Programming Language :: Python :: 3
Classifier: Programming Language :: Python :: 3.9
Classifier: Programming Language :: Python :: 3.10
Classifier: Programming Language :: Python :: 3.11
Requires-Dist: pandas
Requires-Dist: scikit-learn
Requires-Dist: setuptools (>=69.0.3,<70.0.0)
Requires-Dist: statsmodels
